eam_b2c_helper/__init__.py
eam_b2c_helper/b2c.py
eam_b2c_helper-0.1.40.dist-info/METADATA
eam_b2c_helper-0.1.40.dist-info/WHEEL
eam_b2c_helper-0.1.40.dist-info/licenses/LICENSE
eam_b2c_helper-0.1.40.dist-info/RECORD
