Metadata-Version: 2.4
Name: eam_b2c_helper
Version: 0.1.40
Summary: A package to interact with ms graph /users functionality
Author-email: Dave Gunn <daveg@8amsolutions.com>
License-File: LICENSE
Classifier: License :: OSI Approved :: MIT License
Classifier: Operating System :: OS Independent
Classifier: Programming Language :: Python :: 3
Requires-Python: >=3.8
